<?xml version="1.0" encoding="utf-8"?>
<!DOCTYPE dict SYSTEM "apte.dtd">
<?xml-stylesheet href="apte.css" type="text/css" ?>
<dict>
<lexhead no="1">
<dentry>ण</dentry>
<prAwipaxikam>ण</prAwipaxikam>
<grammar>अव्य*</grammar>
<sense no="1">, संस्कृत में ’ण’ से आरम्भ होने वाला कोई शब्द नहीं, ’ण’ से आरम्भ होने वाले बहुत से धातु हैं वस्तुतः वे सब ’न’ से आरम्भ होते हैं, धातुकोश में उन्हें ’ण’ से केवल इसलिए आरम्भ किया गया है जिससे कि यह प्रकट हो जाय कि यहाँ ’न’ प्र, परि तथा अन्तर् आदि उपसर्ग पूर्व होने पर ’ण’ में परिवर्तित हो जाय</sense>
</lexhead>

</dict>
